{
  "version": 1,
  "catalog_version": "2026.07",
  "sources": {
    "dlms-blue17": {"version":"Edition 17 excerpt, 2025-06","url":"https://www.dlms.com/wp-content/uploads/2025/06/Excerpts-DLMS-Blue-Book-Ed-17-part-1-V1.0.pdf"},
    "oms-f121": {"version":"Volume 2 Annex A, issue F121","url":"https://oms-group.org/wp-content/uploads/2024/05/OMS-Spec_Vol2_AnnexA_F121.pdf"},
    "vzlogger": {"version":"master, checked 2026-07","url":"https://github.com/volkszaehler/vzlogger/blob/master/etc/vzlogger.conf"},
    "promotic": {"version":"checked 2026-07; cross-check only","url":"https://www.promotic.eu/en/pmdoc/Subsystems/Comm/PmDrivers/IEC62056_OBIS.htm"}
  },
  "entries": [
    {"code":"1-0:1.8.0","priority":10,"output_name":"Consumption_Total","short":{"de":"Bezogene Wirkenergie, gesamt","en":"Imported active energy, total"},"long":{"de":"Kumulierte elektrische Wirkenergie, die aus dem Netz bezogen wurde.","en":"Cumulative active electrical energy imported from the grid."},"unit":"kWh","category":"active_energy_import","recommended_aggmode":"none","source":"dlms-blue17"},
    {"code":"1-0:1.8.1","priority":11,"output_name":"Consumption_Tarif1","short":{"de":"Bezogene Wirkenergie, Tarif 1","en":"Imported active energy, tariff 1"},"long":{"de":"Kumulierte bezogene Wirkenergie im ersten Tarifregister.","en":"Cumulative imported active energy in the first tariff register."},"unit":"kWh","category":"active_energy_import","recommended_aggmode":"none","source":"dlms-blue17"},
    {"code":"1-0:1.8.2","priority":12,"output_name":"Consumption_Tarif2","short":{"de":"Bezogene Wirkenergie, Tarif 2","en":"Imported active energy, tariff 2"},"long":{"de":"Kumulierte bezogene Wirkenergie im zweiten Tarifregister.","en":"Cumulative imported active energy in the second tariff register."},"unit":"kWh","category":"active_energy_import","recommended_aggmode":"none","source":"dlms-blue17"},
    {"code":"1-0:2.8.0","priority":20,"output_name":"Delivery_Total","short":{"de":"Gelieferte Wirkenergie, gesamt","en":"Exported active energy, total"},"long":{"de":"Kumulierte elektrische Wirkenergie, die in das Netz geliefert wurde.","en":"Cumulative active electrical energy exported to the grid."},"unit":"kWh","category":"active_energy_export","recommended_aggmode":"none","source":"dlms-blue17"},
    {"code":"1-0:1.7.0","priority":30,"output_name":"Consumption_Power","short":{"de":"Bezogene Wirkleistung","en":"Imported active power"},"long":{"de":"Momentane elektrische Wirkleistung in Bezugsrichtung.","en":"Instantaneous active electrical power in the import direction."},"unit":"W","category":"active_power_import","recommended_aggmode":"avg","source":"dlms-blue17"},
    {"code":"1-0:2.7.0","priority":31,"output_name":"Delivery_Power","short":{"de":"Gelieferte Wirkleistung","en":"Exported active power"},"long":{"de":"Momentane elektrische Wirkleistung in Lieferrichtung.","en":"Instantaneous active electrical power in the export direction."},"unit":"W","category":"active_power_export","recommended_aggmode":"avg","source":"dlms-blue17"},
    {"code":"1-0:16.7.0","priority":32,"output_name":"Total_Power","short":{"de":"Wirkleistung, Summe","en":"Total active power"},"long":{"de":"Momentane Summe der elektrischen Wirkleistung über alle verfügbaren Phasen; das Vorzeichen folgt der Zählerrichtung.","en":"Instantaneous sum of active electrical power across all available phases; the sign follows the meter direction."},"unit":"W","category":"active_power_total","recommended_aggmode":"avg","source":"dlms-blue17"},
    {"code":"1-0:32.7.0","priority":40,"output_name":"Voltage_L1","short":{"de":"Spannung L1","en":"Voltage L1"},"long":{"de":"Momentaner Effektivwert der Spannung auf Phase L1.","en":"Instantaneous RMS voltage on phase L1."},"unit":"V","category":"voltage","recommended_aggmode":"avg","source":"dlms-blue17"},
    {"code":"1-0:31.7.0","priority":41,"output_name":"Current_L1","short":{"de":"Strom L1","en":"Current L1"},"long":{"de":"Momentaner Effektivwert des Stroms auf Phase L1.","en":"Instantaneous RMS current on phase L1."},"unit":"A","category":"current","recommended_aggmode":"avg","source":"dlms-blue17"},
    {"code":"7-0:1.8.0","priority":100,"output_name":"Gas_Total","short":{"de":"Gasvolumen, gesamt","en":"Gas volume, total"},"long":{"de":"Kumuliertes, vom Gaszähler erfasstes Volumen.","en":"Cumulative volume recorded by the gas meter."},"unit":"m³","category":"gas_volume","recommended_aggmode":"none","source":"dlms-blue17"},
    {"code":"6-0:1.8.0","priority":110,"output_name":"Water_Total","short":{"de":"Wasservolumen, gesamt","en":"Water volume, total"},"long":{"de":"Kumuliertes, vom Wasserzähler erfasstes Volumen.","en":"Cumulative volume recorded by the water meter."},"unit":"m³","category":"water_volume","recommended_aggmode":"none","source":"dlms-blue17"},
    {"code":"6-0:2.8.0","priority":111,"output_name":"Water_Reverse_Total","short":{"de":"Wasservolumen rückwärts, gesamt","en":"Reverse water volume, total"},"long":{"de":"Kumuliertes Wasservolumen in Rückflussrichtung.","en":"Cumulative water volume in the reverse-flow direction."},"unit":"m³","category":"water_volume_reverse","recommended_aggmode":"none","source":"dlms-blue17"},
    {"code":"5-0:1.8.0","priority":120,"output_name":"Thermal_Energy_Total","short":{"de":"Thermische Energie, gesamt","en":"Thermal energy, total"},"long":{"de":"Kumulierte thermische Energie eines Wärme- oder Kältezählers.","en":"Cumulative thermal energy of a heat or cooling meter."},"unit":"kWh","category":"thermal_energy","recommended_aggmode":"none","source":"dlms-blue17"},
    {"code":"8-0:1.8.0","priority":130,"output_name":"Heat_Cost_Value","short":{"de":"Heizkosten-Verbrauchswert","en":"Heat cost allocation value"},"long":{"de":"Kumulierter dimensionsloser Bewertungswert eines Heizkostenverteilers.","en":"Cumulative dimensionless allocation value from a heat cost allocator."},"unit":"units","category":"heat_cost_allocation","recommended_aggmode":"none","source":"oms-f121","limitations":{"de":"Bei OMS wertet die derzeitige Runtime keinen separaten F-Speicherindex aus.","en":"For OMS, the current runtime does not evaluate a separate F storage index."}},
    {"code":"1-0:96.1.0","priority":200,"output_name":"Server_ID","short":{"de":"Zähler-/Serverkennung","en":"Meter/server identifier"},"long":{"de":"Kennung des logischen Geräts oder Zählers; das konkrete Format ist geräteabhängig.","en":"Identifier of the logical device or meter; its exact format depends on the device."},"unit":"","category":"identifier","recommended_aggmode":"none","source":"dlms-blue17"}
  ],
  "rules": [
    {"priority":1000,"match":{"a":1,"d":7},"short":{"de":"Momentanwert Elektrizität","en":"Instantaneous electricity value"},"long":{"de":"Elektrischer Momentanwert; C bestimmt die Messgröße, E den Tarif oder die Ausprägung.","en":"Instantaneous electrical value; C selects the quantity and E the tariff or variant."},"unit":"","category":"electricity_instantaneous","source":"dlms-blue17"},
    {"priority":1010,"match":{"a":1,"d":8},"short":{"de":"Elektrischer Zählerstand","en":"Electrical cumulative value"},"long":{"de":"Kumulierter elektrischer Zählerstand; C bestimmt Richtung und Messgröße.","en":"Cumulative electrical register; C selects direction and quantity."},"unit":"","category":"electricity_counter","source":"dlms-blue17"},
    {"priority":1100,"match":{"a":7},"short":{"de":"Gas-Messwert","en":"Gas measurement"},"long":{"de":"Messwert eines Gaszählers; die C–E-Gruppen bestimmen Größe und Verarbeitungsart.","en":"Gas meter value; groups C–E identify the quantity and processing."},"unit":"","category":"gas","source":"dlms-blue17"},
    {"priority":1110,"match":{"a":6},"short":{"de":"Wasser-Messwert","en":"Water measurement"},"long":{"de":"Messwert eines Wasserzählers; die C–E-Gruppen bestimmen Größe und Verarbeitungsart.","en":"Water meter value; groups C–E identify the quantity and processing."},"unit":"","category":"water","source":"dlms-blue17"},
    {"priority":1120,"match":{"a":5},"short":{"de":"Thermischer Messwert","en":"Thermal measurement"},"long":{"de":"Messwert eines Wärme- oder Kältezählers.","en":"Value from a heat or cooling meter."},"unit":"","category":"thermal","source":"dlms-blue17"},
    {"priority":1130,"match":{"a":8},"short":{"de":"Heizkostenverteiler-Wert","en":"Heat cost allocator value"},"long":{"de":"Mess- oder Servicewert eines Heizkostenverteilers.","en":"Measurement or service value from a heat cost allocator."},"unit":"","category":"heat_cost_allocation","source":"oms-f121"},
    {"priority":1900,"match":{"c":96},"short":{"de":"Service- oder Identifikationswert","en":"Service or identification value"},"long":{"de":"Abstrakter Identifikations-, Status- oder Servicewert; die konkrete Bedeutung hängt von D und E ab.","en":"Abstract identification, status, or service value; groups D and E determine the specific meaning."},"unit":"","category":"service","source":"dlms-blue17"}
  ]
}
